__init__.py
git_interviewer/__init__.py
git_interviewer/cli.py
git_interviewer/config.py
git_interviewer/git_utils.py
git_interviewer/llm.py
git_interviewer/main.py
git_interviewer/personas.py
git_interviewer-1.0.0.dist-info/METADATA
git_interviewer-1.0.0.dist-info/WHEEL
git_interviewer-1.0.0.dist-info/entry_points.txt
git_interviewer-1.0.0.dist-info/top_level.txt
git_interviewer-1.0.0.dist-info/RECORD
