Metadata-Version: 2.4
Name: git-interviewer
Version: 1.0.0
Summary: A pre-commit hook that interviews you about your code.
Author-email: Naman Rusia <naman.rusia14@gmail.com>
Requires-Python: >=3.9
Requires-Dist: typer[all]>=0.9.0
Requires-Dist: click==8.1.7
Requires-Dist: rich>=13.0.0
Requires-Dist: google-genai
Requires-Dist: python-dotenv>=1.0.0
